bricker/__init__.py
bricker-0.6.0.dist-info/LICENSE.txt
bricker-0.6.0.dist-info/METADATA
bricker-0.6.0.dist-info/WHEEL
bricker-0.6.0.dist-info/entry_points.txt
bricker-0.6.0.dist-info/top_level.txt
bricker-0.6.0.dist-info/RECORD
